openfaceid/__init__.py
openfaceid/face_detector.py
openfaceid/models/dlib_face_recognition_resnet_model_v1.dat
openfaceid/models/shape_predictor_5_face_landmarks.dat
openfaceid/vector_stores/__init__.py
openfaceid/vector_stores/faiss.py
openfaceid/vector_stores/pinecone.py
openfaceid/vector_stores/vector_store.py
openfaceid-0.1.4.dist-info/LICENSE
openfaceid-0.1.4.dist-info/METADATA
openfaceid-0.1.4.dist-info/WHEEL
openfaceid-0.1.4.dist-info/RECORD
