Metadata-Version: 2.1
Name: openfaceid
Version: 0.1.4
Summary: Identity Verification with Facial Recognition
Home-page: https://github.com/ahalimkara/openfaceid
License: Apache-2.0
Author: Abdulhalim Kara
Author-email: ahalimkara@gmail.com
Requires-Python: >=3.9,<4.0
Classifier: Development Status :: 1 - Planning
Classifier: License :: OSI Approved :: Apache Software License
Classifier: Operating System :: OS Independent
Classifier: Programming Language :: Python
Classifier: Programming Language :: Python :: 3
Classifier: Programming Language :: Python :: 3.9
Classifier: Programming Language :: Python :: 3.10
Classifier: Programming Language :: Python :: 3.11
Classifier: Programming Language :: Python :: 3 :: Only
Provides-Extra: all
Requires-Dist: dlib (>=19.24.2,<20.0.0)
Requires-Dist: faiss-cpu (>=1,<2) ; extra == "all"
Requires-Dist: numpy (>=1.25.1,<2.0.0)
Requires-Dist: pillow (>=10.0.0,<11.0.0)
Requires-Dist: pinecone-client (>=2.2.2,<3.0.0) ; extra == "all"
Requires-Dist: pytest-vcr (>=1.0.2,<2.0.0) ; extra == "all"
Project-URL: Repository, https://github.com/ahalimkara/openfaceid
